MANIFEST.in
README.rst
configit.py
setup.py
ConfigIt.egg-info/PKG-INFO
ConfigIt.egg-info/SOURCES.txt
ConfigIt.egg-info/dependency_links.txt
ConfigIt.egg-info/top_level.txt
tests/__init__.py
tests/test_conf_from_file.py
tests/test_conf_from_module.py
tests/test_configdict.py
tests/test_moduleconfig.py
tests/test_use_config.py
tests/test_version.py