Metadata-Version: 1.1
Name: ConfigIt
Version: 1.1
Summary: Python Configurations
Home-page: https://github.com/pictage/ConfigIt
Author: Pictage
Author-email: dev@pictage.com
License: MIT License
Keywords: configuration
Platform: UNKNOWN
Classifier: Development Status :: 5 - Production/Stable
Classifier: Topic :: Utilities
Classifier: License :: OSI Approved :: MIT License
Classifier: Programming Language :: Python :: 2.6
Classifier: Programming Language :: Python :: 2.7
Classifier: Programming Language :: Python :: 3.2
